atpplots/__init__.py
atpplots/axis.py
atpplots/bars.py
atpplots/confusion_matrix.py
atpplots/curve.py
atpplots/curve_vector.py
atpplots/datavector.py
atpplots/figure.py
atpplots/hist.py
atpplots/scatter.py
atpplots-0.0.6.dist-info/LICENSE
atpplots-0.0.6.dist-info/METADATA
atpplots-0.0.6.dist-info/WHEEL
atpplots-0.0.6.dist-info/top_level.txt
atpplots-0.0.6.dist-info/RECORD
